[{"ipprefix": "github.com/GoogleCloudPlatform/kubernetes","package":"kubernetes"},
{"ipprefix": "github.com/GoogleCloudPlatform/gcloud-golang","package":"golang-google-golangorg-cloud"},
{"ipprefix": "github.com/google/cadvisor","package":"cadvisor"},
{"ipprefix": "github.com/docker/docker","package":"docker"},
{"ipprefix": "github.com/docker/distribution","package":"docker-distribution"},
{"ipprefix": "github.com/coreos/etcd","package":"etcd"},
{"ipprefix": "github.com/coreos/fleet","package":"fleet"},
{"ipprefix": "github.com/golang/crypto","package":"golang-googlecode-crypto"},
{"ipprefix": "github.com/pborman/uuid","package":"golang-googlecode-uuid"},
{"ipprefix": "code.google.com/p/google-api-go-client","package":"golang-googlecode-google-api-client"},
{"ipprefix": "code.google.com/p/go.net","package":"golang-googlecode-net"},
{"ipprefix": "code.google.com/p/go-uuid","package":"golang-googlecode-uuid"},
{"ipprefix": "code.google.com/p/go.text","package":"golang-googlecode-text"},
{"ipprefix": "code.google.com/p/go.exp","package":"golang-googlecode-go-exp"},
{"ipprefix": "code.google.com/p/go.crypto","package":"golang-googlecode-go-crypto"},
{"ipprefix": "golang.org/x/net","package":"golang-googlecode-net"},
{"ipprefix": "golang.org/x/text","package":"golang-googlecode-text"},
{"ipprefix": "golang.org/x/oauth2","package":"golang-googlecode-goauth2"},
{"ipprefix": "golang.org/x/crypto","package":"golang-googlecode-go-crypto"},
{"ipprefix": "golang.org/x/sys","package":"golang-github-golang-sys"},
{"ipprefix": "gopkg.in/check.v1","package":"golang-gopkg-check"},
{"ipprefix": "github.com/motain/gocheck","package":"golang-gopkg-check"},
{"ipprefix": "gopkg.in/v1/check","package":"golang-gopkg-check"},
{"ipprefix": "gopkg.in/v2/yaml","package":"golang-gopkg-yaml"},
{"ipprefix": "gopkg.in/yaml.v2","package":"golang-gopkg-yaml"},
{"ipprefix": "gopkg.in/yaml.v1","package":"golang-gopkg-yaml"},
{"ipprefix": "github.com/golang/protobuf","package":"golang-googlecode-goprotobuf"},
{"ipprefix": "github.com/gogo/protobuf","package":"golang-googlecode-gogoprotobuf"},
{"ipprefix": "camlistore.org","package":"camlistore"},
{"ipprefix": "google.golang.org/grpc","package":"golang-github-grpc-grpc-go"},
{"ipprefix": "k8s.io/heapster", "package": "golang-github-kubernetes-heapster"}]
